cryptograpy.py
cryptograpy-0.0.0.dist-info/LICENSE
cryptograpy-0.0.0.dist-info/WHEEL
cryptograpy-0.0.0.dist-info/METADATA
cryptograpy-0.0.0.dist-info/RECORD
