Metadata-Version: 1.1
Name: cryptograpy
Version: 0.0.0
Summary: Did you mean cryptograp*h*y?
Home-page: https://github.com/graingert/cryptograpy
Author: Thomas Grainger
Author-email: cryptograpy@graingert.co.uk
